sen2sr/__init__.py
sen2sr/models/__init__.py
sen2sr/models/opensr_baseline/__init__.py
sen2sr/models/opensr_baseline/cnn.py
sen2sr/models/opensr_baseline/mamba.py
sen2sr/models/opensr_baseline/swin.py
sen2sr/models/tricks.py
sen2sr/nonreference.py
sen2sr/referencex2.py
sen2sr/referencex4.py
sen2sr/utils.py
sen2sr/xai/__init__.py
sen2sr/xai/lam.py
sen2sr/xai/utils.py
sen2sr-0.8.5.dist-info/LICENSE
sen2sr-0.8.5.dist-info/METADATA
sen2sr-0.8.5.dist-info/WHEEL
sen2sr-0.8.5.dist-info/RECORD
