Metadata-Version: 2.1
Name: sen2sr
Version: 0.8.5
Summary: A Python package to super-resolve Sentinel-2 satellite imagery up to 2.5 meters.
Home-page: https://github.com/ESAOpenSR/sen2sr
Author: Cesar Aybar
Author-email: cesar.aybar@uv.es
Requires-Python: >=3.10,<4.0
Classifier: Programming Language :: Python :: 3
Classifier: Programming Language :: Python :: 3.10
Classifier: Programming Language :: Python :: 3.11
Classifier: Programming Language :: Python :: 3.12
Requires-Dist: einops (>=0.8.1)
Requires-Dist: numpy (>=2.0.2)
Requires-Dist: timm (>=1.0.15)
Requires-Dist: tqdm (>=4.67.1)
Project-URL: Documentation, https://esaopensr.github.io/sen2sr/
Project-URL: Repository, https://github.com/ESAOpenSR/sen2sr
